<annotation>
  <folder>gtsdb_copy</folder>
  <filename>00841</filename>
  <path>D:/Gatech/ml/GRA/gtsdb_copy/00841.ppm</path>
  <source>
    <database>Unknown</database>
  </source>
  <size>
    <width>1360</width>
    <height>800</height>
    <depth>3</depth>
  </size>
  <segmented>0</segmented>
  <object>
    <name>43</name>
    <pose>Unspecified</pose>
    <truncated>0</truncated>
    <difficult>0</difficult>
    <bndbox>
      <xmin>891</xmin>
      <ymin>391</ymin>
      <xmax>908</xmax>
      <ymax>411</ymax>
    </bndbox>
  </object>
</annotation>
